nibo_api/__init__.py
nibo_api/settings.py
nibo_api/common/__init__.py
nibo_api/common/client.py
nibo_api/common/exceptions.py
nibo_api/common/models.py
nibo_api/empresa/__init__.py
nibo_api/empresa/arquivos.py
nibo_api/empresa/categorias.py
nibo_api/empresa/centro_custo.py
nibo_api/empresa/client.py
nibo_api/empresa/cobrancas.py
nibo_api/empresa/conciliacao.py
nibo_api/empresa/contas_extratos.py
nibo_api/empresa/nota_fiscal.py
nibo_api/empresa/organizacoes.py
nibo_api/empresa/parcelamentos.py
nibo_api/empresa/relatorios.py
nibo_api/empresa/agendamentos/__init__.py
nibo_api/empresa/agendamentos/anotacoes.py
nibo_api/empresa/agendamentos/arquivos.py
nibo_api/empresa/agendamentos/pagamentos.py
nibo_api/empresa/agendamentos/pagar.py
nibo_api/empresa/agendamentos/receber.py
nibo_api/empresa/agendamentos/recebimentos.py
nibo_api/empresa/contatos/__init__.py
nibo_api/empresa/contatos/clientes.py
nibo_api/empresa/contatos/fornecedores.py
nibo_api/empresa/contatos/funcionarios.py
nibo_api/empresa/contatos/socios.py
nibo_api/empresa/management/__init__.py
nibo_api/empresa/management/cli.py
nibo_api/empresa/management/utils.py
nibo_api/empresa/management/commands/__init__.py
nibo_api/empresa/management/commands/agendamentos.py
nibo_api/empresa/management/commands/categorias.py
nibo_api/empresa/management/commands/clientes.py
nibo_api/empresa/management/commands/fornecedores.py
nibo_api/empresa/management/commands/organizacoes.py
nibo_api/obrigacoes/__init__.py
nibo_api/obrigacoes/arquivos.py
nibo_api/obrigacoes/client.py
nibo_api/obrigacoes/clientes.py
nibo_api/obrigacoes/cnaes.py
nibo_api/obrigacoes/conferencia.py
nibo_api/obrigacoes/contatos.py
nibo_api/obrigacoes/departamentos.py
nibo_api/obrigacoes/escritorios.py
nibo_api/obrigacoes/grupos_clientes.py
nibo_api/obrigacoes/relatorios.py
nibo_api/obrigacoes/responsabilidades.py
nibo_api/obrigacoes/tarefas.py
nibo_api/obrigacoes/templates_tarefas.py
nibo_api/obrigacoes/usuarios.py
nibo_api/obrigacoes/management/__init__.py
nibo_api-0.1.0.dist-info/licenses/LICENSE
nibo_api-0.1.0.dist-info/METADATA
nibo_api-0.1.0.dist-info/WHEEL
nibo_api-0.1.0.dist-info/entry_points.txt
nibo_api-0.1.0.dist-info/top_level.txt
nibo_api-0.1.0.dist-info/RECORD
