Metadata-Version: 2.4
Name: nibo-api
Version: 0.1.0
Summary: Cliente Python para integração com as APIs Nibo (Empresa e Obrigações)
Author: Nibo API Contributors
License: MIT License
Project-URL: Homepage, https://github.com/ismaelnjr/nibo-api
Project-URL: Documentation, https://github.com/ismaelnjr/nibo-api/blob/main/README.md
Project-URL: Repository, https://github.com/ismaelnjr/nibo-api
Project-URL: Issues, https://github.com/ismaelnjr/nibo-api/issues
Keywords: nibo,api,financeiro,obrigacoes,contabilidade
Classifier: Development Status :: 4 - Beta
Classifier: Intended Audience :: Developers
Classifier: License :: OSI Approved :: MIT License
Classifier: Programming Language :: Python :: 3
Classifier: Programming Language :: Python :: 3.7
Classifier: Programming Language :: Python :: 3.8
Classifier: Programming Language :: Python :: 3.9
Classifier: Programming Language :: Python :: 3.10
Classifier: Programming Language :: Python :: 3.11
Classifier: Programming Language :: Python :: 3.12
Classifier: Topic :: Software Development :: Libraries :: Python Modules
Classifier: Topic :: Office/Business :: Financial
Requires-Python: >=3.7
License-File: LICENSE
Requires-Dist: requests>=2.31.0
Requires-Dist: cryptography>=41.0.0
Provides-Extra: dev
Requires-Dist: pytest>=7.0.0; extra == "dev"
Requires-Dist: pytest-cov>=4.0.0; extra == "dev"
Dynamic: license-file
